telegram_game/__init__.py
telegram_game/api.py
telegram_game/cli.py
telegram_game/dispatcher.py
telegram_game/game.py
telegram_game/messages.py
telegram_game/redis_game.py
telegram_game-0.0.3.dist-info/DESCRIPTION.rst
telegram_game-0.0.3.dist-info/METADATA
telegram_game-0.0.3.dist-info/RECORD
telegram_game-0.0.3.dist-info/WHEEL
telegram_game-0.0.3.dist-info/entry_points.txt
telegram_game-0.0.3.dist-info/metadata.json
telegram_game-0.0.3.dist-info/pbr.json
telegram_game-0.0.3.dist-info/top_level.txt
